async_wrapper/__init__.py
async_wrapper/exception.py
async_wrapper/pipe.py
async_wrapper/py.typed
async_wrapper/queue.py
async_wrapper/wait.py
async_wrapper/convert/__init__.py
async_wrapper/convert/_async.py
async_wrapper/convert/main.py
async_wrapper/convert/_sync/__init__.py
async_wrapper/convert/_sync/main.py
async_wrapper/convert/_sync/sqlalchemy.py
async_wrapper/task_group/__init__.py
async_wrapper/task_group/task_group.py
async_wrapper/task_group/value.py
async_wrapper-0.11.1.dist-info/METADATA
async_wrapper-0.11.1.dist-info/WHEEL
async_wrapper-0.11.1.dist-info/licenses/LICENSE
async_wrapper-0.11.1.dist-info/RECORD
