Metadata-Version: 2.3
Name: async-wrapper
Version: 0.11.1
Summary: async wrapper
Project-URL: Documentation, https://async-wrapper.readthedocs.io/
Project-URL: Repository, https://github.com/phi-friday/async-wrapper
Author-email: phi <phi.friday@gmail.com>
License: MIT License
License-File: LICENSE
Classifier: Development Status :: 4 - Beta
Classifier: Framework :: AnyIO
Classifier: Framework :: AsyncIO
Classifier: Framework :: Trio
Classifier: Programming Language :: Python :: 3
Classifier: Programming Language :: Python :: 3.9
Classifier: Programming Language :: Python :: 3.10
Classifier: Programming Language :: Python :: 3.11
Classifier: Programming Language :: Python :: 3.12
Classifier: Programming Language :: Python :: 3.13
Classifier: Programming Language :: Python :: Implementation :: CPython
Requires-Python: >=3.9
Requires-Dist: anyio>=4.0.0
Requires-Dist: exceptiongroup; python_version < '3.11'
Requires-Dist: sniffio>=1.3.1
Requires-Dist: typing-extensions>=4.4.0
Provides-Extra: docs
Requires-Dist: readthedocs-sphinx-search>=0.3.2; extra == 'docs'
Requires-Dist: sphinx-mdinclude>=0.5.3; extra == 'docs'
Requires-Dist: sphinx-rtd-theme>=2.0.0; extra == 'docs'
Requires-Dist: sphinx>=7.1.0; extra == 'docs'
Provides-Extra: sqlalchemy
Requires-Dist: greenlet; extra == 'sqlalchemy'
Requires-Dist: sqlalchemy[asyncio]; extra == 'sqlalchemy'
Provides-Extra: test
Requires-Dist: aiosqlite>=0.20.0; extra == 'test'
Requires-Dist: pytest-cov>=5.0.0; extra == 'test'
Requires-Dist: pytest-xdist>=3.6.1; extra == 'test'
Requires-Dist: pytest>=8.0.0; extra == 'test'
Requires-Dist: trio>=0.24.0; extra == 'test'
Provides-Extra: uvloop
Requires-Dist: uvloop; (platform_system != 'Windows') and extra == 'uvloop'
